{
  "timestamp": "2026-05-15T14:47:02+0000",
  "articles": [
    {
      "title": "What next for Starmer? Five scenarios in Labour leadership crisis",
      "link": "https://www.bbc.com/news/articles/cyv26q0g9r1o?at_medium=RSS&at_campaign=rss",
      "published": "Fri, 15 May 2026 14:40:11 GMT",
      "description": "There's a chance Andy Burnham's bid to become an MP will fail, and Sir Keir Starmer could fight on as PM.",
      "source": "BBC News",
      "category": "Global"
    },
    {
      "title": "Brutal raid on woman's birthday party highlights rise of Russian vigilante group",
      "link": "https://www.bbc.com/news/articles/cq5p306l7weo?at_medium=RSS&at_campaign=rss",
      "published": "Fri, 15 May 2026 00:04:45 GMT",
      "description": "The Russkaya Obshina group stages raids to look for activities contravening\n\"traditional Russian values\".",
      "source": "BBC News",
      "category": "Global"
    },
    {
      "title": "Trump says he 'made no commitment either way' to Xi on Taiwan",
      "link": "https://www.bbc.com/news/articles/ce8p61v7l68o?at_medium=RSS&at_campaign=rss",
      "published": "Fri, 15 May 2026 14:13:36 GMT",
      "description": "Trump said Xi Jinping had asked directly if the US would defend Taiwan, and he had responded, \"I don't talk about that\".",
      "source": "BBC News",
      "category": "Global"
    },
    {
      "title": "Five Italians die during cave scuba dive in Maldives",
      "link": "https://www.bbc.com/news/articles/c62e0p7rd2ro?at_medium=RSS&at_campaign=rss",
      "published": "Fri, 15 May 2026 07:38:17 GMT",
      "description": "Four of the Italians were part of a team from the University of Genoa.",
      "source": "BBC News",
      "category": "Global"
    },
    {
      "title": "Gempa 6,3 magnitudo guncang Jepang, tanpa peringatan tsunami",
      "link": "https://www.antaranews.com/berita/5569167/gempa-63-magnitudo-guncang-jepang-tanpa-peringatan-tsunami",
      "published": "Fri, 15 May 2026 21:43:26 +0700",
      "description": "Gempa dengan magnitudo awal 6,3 mengguncang Jepang timur laut pada Jumat tanpa peringatan tsunami, menurut Badan ...",
      "source": "Antara News",
      "category": "Indonesia"
    },
    {
      "title": "Ini kata TNI AD terkait Film \"Pesta Babi\" di Papua",
      "link": "https://www.antaranews.com/berita/5569164/ini-kata-tni-ad-terkait-film-pesta-babi-di-papua",
      "published": "Fri, 15 May 2026 21:42:24 +0700",
      "description": "TNI AD mengimbau warga untuk bijak dalam menyikapi maraknya rencana pemutaran film dokumenter &ldquo;Pesta Babi&rdquo; ...",
      "source": "Antara News",
      "category": "Indonesia"
    },
    {
      "title": "Pameran Karya Kreatif NTB 2026 persiapkan 119 UMKM merambah pasar luar",
      "link": "https://www.antaranews.com/video/5569159/pameran-karya-kreatif-ntb-2026-persiapkan-119-umkm-merambah-pasar-luar",
      "published": "Fri, 15 May 2026 21:42:02 +0700",
      "description": "ANTARA -&nbsp;Pameran Karya Kreatif Nusa Tenggara Barat, kembali hadir di tahun 2026 dengan melibatkan 119 Usaha Mikro ...",
      "source": "Antara News",
      "category": "Indonesia"
    },
    {
      "title": "Carrick mainkan Casemiro dalam laga perpisahan di Old Trafford",
      "link": "https://www.antaranews.com/berita/5569156/carrick-mainkan-casemiro-dalam-laga-perpisahan-di-old-trafford",
      "published": "Fri, 15 May 2026 21:35:24 +0700",
      "description": "Pelatih Manchester United Michael Carrick memastikan gelandang senior Casemiro akan melakoni laga perpisahan di Old ...",
      "source": "Antara News",
      "category": "Indonesia"
    }
  ]
}