{
  "timestamp": "2026-06-27T03:52:13+0000",
  "articles": [
    {
      "title": "US conducts strikes on Iran after attack on cargo ship",
      "link": "https://www.bbc.co.uk/news/articles/ckg590wqxwpo?at_medium=RSS&at_campaign=rss",
      "published": "Sat, 27 Jun 2026 02:48:12 GMT",
      "description": "US Central Command says it has struck missile and drone storage facilities and coastal radar positions.",
      "source": "BBC News",
      "category": "Global"
    },
    {
      "title": "Home Office to introduce new asylum routes to UK",
      "link": "https://www.bbc.co.uk/news/articles/c5yz952dm74o?at_medium=RSS&at_campaign=rss",
      "published": "Sat, 27 Jun 2026 01:03:00 GMT",
      "description": "The home secretary said \"capped safe and legal\" routes would help to restore confidence in the asylum system.",
      "source": "BBC News",
      "category": "Global"
    },
    {
      "title": "Hottest June day record broken for third day in row as temperature hits 37.3C",
      "link": "https://www.bbc.co.uk/news/articles/cn4d0n1l8zno?at_medium=RSS&at_campaign=rss",
      "published": "Sat, 27 Jun 2026 03:25:44 GMT",
      "description": "Suffolk saw the highest temperature on Friday - but many will feel the heatwave begin to ease over the weekend.",
      "source": "BBC News",
      "category": "Global"
    },
    {
      "title": "Venezuela earthquakes kill 920 people as families desperate for news",
      "link": "https://www.bbc.co.uk/news/articles/c39y79g7gzko?at_medium=RSS&at_campaign=rss",
      "published": "Fri, 26 Jun 2026 21:15:37 GMT",
      "description": "Hundreds are still feared trapped under the rubble, as international rescue teams start to arrive.",
      "source": "BBC News",
      "category": "Global"
    },
    {
      "title": "Media: Oman ingatkan Eropa soal tarif lewati Selat Hormuz",
      "link": "https://www.antaranews.com/berita/5625188/media-oman-ingatkan-eropa-soal-tarif-lewati-selat-hormuz",
      "published": "Sat, 27 Jun 2026 10:51:39 +0700",
      "description": "Oman telah memberitahu negara-negara Eropa bahwa pihaknya mungkin akan mengenakan biaya pada kapal-kapal yang berlayar ...",
      "source": "Antara News",
      "category": "Indonesia"
    },
    {
      "title": "Pemkab Kukar naikkan dana RT jadi Rp150 juta per tahun",
      "link": "https://www.antaranews.com/berita/5625184/pemkab-kukar-naikkan-dana-rt-jadi-rp150-juta-per-tahun",
      "published": "Sat, 27 Jun 2026 10:48:19 +0700",
      "description": "Pemerintah Kabupaten Kutai Kartanegara (Kukar), Kalimantan Timur, menaikkan dana setiap rukun tetangga (RT) dari ...",
      "source": "Antara News",
      "category": "Indonesia"
    },
    {
      "title": "Sabtu ini harga emas tiga jenama di Pegadaian serempak naik",
      "link": "https://www.antaranews.com/berita/5625181/sabtu-ini-harga-emas-tiga-jenama-di-pegadaian-serempak-naik",
      "published": "Sat, 27 Jun 2026 10:39:28 +0700",
      "description": "Harga emas di laman Pegadaian, yang dikutip di Jakarta, Sabtu, pukul 10.34 WIB, menunjukkan untuk&nbsp;jenama Galeri24, ...",
      "source": "Antara News",
      "category": "Indonesia"
    },
    {
      "title": "Sahroni: Meningkatnya kepercayaan publik bukti kinerja Polri berdampak",
      "link": "https://www.antaranews.com/berita/5625177/sahroni-meningkatnya-kepercayaan-publik-bukti-kinerja-polri-berdampak",
      "published": "Sat, 27 Jun 2026 10:35:51 +0700",
      "description": "Wakil Ketua Komisi III DPR RI&nbsp;Ahmad Sahroni&nbsp;menilai meningkatnya kepercayaan publik terhadap Polri ...",
      "source": "Antara News",
      "category": "Indonesia"
    }
  ]
}