{
  "timestamp": "2026-05-20T23:13:09+0000",
  "articles": [
    {
      "title": "Russian jets 'dangerously' intercept RAF spy plane over Black Sea",
      "link": "https://www.bbc.com/news/articles/cq8p40e2zx1o?at_medium=RSS&at_campaign=rss",
      "published": "Wed, 20 May 2026 16:00:05 GMT",
      "description": "The unarmed Rivet Joint surveillance aircraft was conducting a \"routine international flight\" during the incidents, the Ministry of Defence says.",
      "source": "BBC News",
      "category": "Global"
    },
    {
      "title": "Women who died in sea off Brighton were sisters",
      "link": "https://www.bbc.com/news/articles/c62dn5r4elqo?at_medium=RSS&at_campaign=rss",
      "published": "Wed, 20 May 2026 20:23:02 GMT",
      "description": "Paying tribute, their father says \"no words can truly describe the pain of losing three daughters\".",
      "source": "BBC News",
      "category": "Global"
    },
    {
      "title": "Why illegal children's homes are being paid up to £2m per child by councils",
      "link": "https://www.bbc.com/news/articles/cwy2vxp48y8o?at_medium=RSS&at_campaign=rss",
      "published": "Wed, 20 May 2026 23:10:10 GMT",
      "description": "A ban was meant to bring an end to the practice - but councils continue to fund illegal placements.",
      "source": "BBC News",
      "category": "Global"
    },
    {
      "title": "Southampton lose appeal against play-off expulsion",
      "link": "https://www.bbc.com/sport/football/articles/cn4p284ny2ko?at_medium=RSS&at_campaign=rss",
      "published": "Wed, 20 May 2026 21:15:29 GMT",
      "description": "Southampton lose their appeal against expulsion from the Championship play-off final for spying.",
      "source": "BBC News",
      "category": "Global"
    },
    {
      "title": "Aktor Benidictus Siregar sebut masih suka dipanggil Juna Sekawan Limo",
      "link": "https://www.antaranews.com/berita/5575881/aktor-benidictus-siregar-sebut-masih-suka-dipanggil-juna-sekawan-limo",
      "published": "Thu, 21 May 2026 06:10:44 +0700",
      "description": "Komedian Benidictus Siregar mengatakan perannya sebagai Juna dalam film &quot;Sekawan Limo&quot; (2024) telah merintis ...",
      "source": "Antara News",
      "category": "Indonesia"
    },
    {
      "title": "Aktris cilik Ellea Candice buat sang ibu ikut akting Sekawan Limo 2",
      "link": "https://www.antaranews.com/berita/5575875/aktris-cilik-ellea-candice-buat-sang-ibu-ikut-akting-sekawan-limo-2",
      "published": "Thu, 21 May 2026 06:06:30 +0700",
      "description": "Aktris berusia enam tahun Ellea Candice ikut terlibat dalam produksi film komedi horor terbaru garapan sutradara Bayu ...",
      "source": "Antara News",
      "category": "Indonesia"
    },
    {
      "title": "Hasil menata kembali daerah terdampak bencana Sumatera",
      "link": "https://www.antaranews.com/infografik/5574380/hasil-menata-kembali-daerah-terdampak-bencana-sumatera",
      "published": "Thu, 21 May 2026 06:00:00 +0700",
      "description": "Pemerintah gencar menata kembali roda perekonomian di daerah terdampak bencana di Sumatera. Hingga Mei 2026, upaya ...",
      "source": "Antara News",
      "category": "Indonesia"
    },
    {
      "title": "Inter Miami dikabarkan segera datangkan Casemiro di musim panas ini",
      "link": "https://www.antaranews.com/berita/5575873/inter-miami-dikabarkan-segera-datangkan-casemiro-di-musim-panas-ini",
      "published": "Thu, 21 May 2026 05:58:11 +0700",
      "description": "Klub Major League Soccer (MLS), Inter Miami dikabarkan segera mendatangkan gelandang Brasil, Casemiro pada bursa ...",
      "source": "Antara News",
      "category": "Indonesia"
    }
  ]
}