{
  "timestamp": "2026-05-18T21:47:26+0000",
  "articles": [
    {
      "title": "Married at First Sight UK brides tell BBC they were raped by on-screen husbands",
      "link": "https://www.bbc.com/news/articles/cp8pz1k4r2lo?at_medium=RSS&at_campaign=rss",
      "published": "Mon, 18 May 2026 16:53:12 GMT",
      "description": "Channel 4 was aware of one of the rape claims before broadcast, but the woman involved still featured in the show.",
      "source": "BBC News",
      "category": "Global"
    },
    {
      "title": "Burnham pledges not to 're-run' Brexit arguments",
      "link": "https://www.bbc.com/news/articles/cx21en4807wo?at_medium=RSS&at_campaign=rss",
      "published": "Mon, 18 May 2026 17:03:24 GMT",
      "description": "The potential leadership challenger says he is not proposing the UK considers rejoining the EU.",
      "source": "BBC News",
      "category": "Global"
    },
    {
      "title": "New High Street crime unit to target gangs fronting shops after BBC investigation",
      "link": "https://www.bbc.com/news/articles/ce3pzwx449no?at_medium=RSS&at_campaign=rss",
      "published": "Mon, 18 May 2026 21:06:38 GMT",
      "description": "It follows BBC News exposing drug gangs, money laundering, immigration crime, and ghost directors linked to shop fronts.",
      "source": "BBC News",
      "category": "Global"
    },
    {
      "title": "Trump says he called off new Iran attack at request of Gulf states",
      "link": "https://www.bbc.com/news/articles/c7079e55zjro?at_medium=RSS&at_campaign=rss",
      "published": "Mon, 18 May 2026 21:09:35 GMT",
      "description": "The US president says he is holding off on a US attack planned for Tuesday as \"serious negotiations are now taking place\".",
      "source": "BBC News",
      "category": "Global"
    },
    {
      "title": "Anggota DEN sebut tingkat kesulitan Blok Ganal tinggi",
      "link": "https://www.antaranews.com/berita/5572379/anggota-den-sebut-tingkat-kesulitan-blok-ganal-tinggi",
      "published": "Tue, 19 May 2026 04:28:40 +0700",
      "description": "Anggota Dewan Energi Nasional (DEN) Muhammad Kholid Syeirazi menyebutkan Blok Ganal termasuk ke dalam Indonesia ...",
      "source": "Antara News",
      "category": "Indonesia"
    },
    {
      "title": "Sulteng perkuat literasi keuangan untuk generasi muda",
      "link": "https://www.antaranews.com/berita/5572377/sulteng-perkuat-literasi-keuangan-untuk-generasi-muda",
      "published": "Tue, 19 May 2026 03:35:11 +0700",
      "description": "Pemerintah Kota Palu bersama lembaga edukasi dan literasi, Hanna Asa Indonesia memperkuat kolaborasi untuk meningkatkan ...",
      "source": "Antara News",
      "category": "Indonesia"
    },
    {
      "title": "DPD RI dukung industri kreatif dan musik di Kaltara",
      "link": "https://www.antaranews.com/berita/5572373/dpd-ri-dukung-industri-kreatif-dan-musik-di-kaltara",
      "published": "Tue, 19 May 2026 03:16:43 +0700",
      "description": "Anggota Dewan Perwakilan Daerah Republik Indonesia,&nbsp;Herman&nbsp;di Tarakan, Senin, menyatakan mendukung penuh ...",
      "source": "Antara News",
      "category": "Indonesia"
    },
    {
      "title": "Dituntut 5 tahun bui, eks Wamenaker Noel: Mending saya korupsi banyak",
      "link": "https://www.antaranews.com/berita/5572369/dituntut-5-tahun-bui-eks-wamenaker-noel-mending-saya-korupsi-banyak",
      "published": "Tue, 19 May 2026 03:13:41 +0700",
      "description": "Wakil Menteri Ketenagakerjaan periode 2024&ndash;2025 Immanuel &quot;Noel&quot; Ebenezer Gerungan mengaku menyesal ...",
      "source": "Antara News",
      "category": "Indonesia"
    }
  ]
}